grobid2json/__init__.py
grobid2json/__version__.py
grobid2json/citation_util.py
grobid2json/grobid_util.py
grobid2json/main.py
grobid2json/refspan_util.py
grobid2json/s2orc.py
grobid2json-0.0.1.dist-info/LICENSE
grobid2json-0.0.1.dist-info/METADATA
grobid2json-0.0.1.dist-info/WHEEL
grobid2json-0.0.1.dist-info/entry_points.txt
grobid2json-0.0.1.dist-info/top_level.txt
grobid2json-0.0.1.dist-info/RECORD
