Metadata-Version: 2.1
Name: grobid2json
Version: 0.0.1
Summary: grobid2json
Home-page: https://sitoi.cn
Author: Sitoi
Author-email: 133397418@qq.com
License: MIT
Project-URL: Documentation, https://sitoi.github.io/grobid2json/
Classifier: License :: OSI Approved :: MIT License
Classifier: Programming Language :: Python :: 3.9
Classifier: Programming Language :: Python :: Implementation :: CPython
Classifier: Programming Language :: Python :: Implementation :: PyPy
Requires-Python: >=3.9.0
License-File: LICENSE
Requires-Dist: beautifulsoup4 ==4.12.2
